orm_database/__init__.py
orm_database/orm_database.py
orm_database/orm_query.py
orm_database-0.3.27.dist-info/licenses/LICENSE
orm_database-0.3.27.dist-info/METADATA
orm_database-0.3.27.dist-info/WHEEL
orm_database-0.3.27.dist-info/top_level.txt
orm_database-0.3.27.dist-info/RECORD
