Metadata-Version: 2.4
Name: orm_database
Version: 0.3.27
Summary: This module is written to launch your programs with any database you want in the shortest time 
Home-page: https://github.com/sisrsis/orm-database
Author: SISRSIS
Author-email: virussisrsis@gmail.com
License: MIT
License-File: LICENSE
Requires-Dist: asyncpg
Requires-Dist: motor
Requires-Dist: mariadb
Dynamic: author
Dynamic: author-email
Dynamic: description
Dynamic: description-content-type
Dynamic: home-page
Dynamic: license
Dynamic: license-file
Dynamic: requires-dist
Dynamic: summary
